goma/__init__.py
goma/basematch.py
goma/exactmatch.py
goma/prioritymatch.py
goma-0.2.dist-info/LICENSE
goma-0.2.dist-info/METADATA
goma-0.2.dist-info/WHEEL
goma-0.2.dist-info/top_level.txt
goma-0.2.dist-info/RECORD
